PieperKine/PieperKine.cp310-win_amd64.pyd
PieperKine/PieperKine.cpython-310-x86_64-linux-gnu.so
PieperKine/__init__.py
pieperkine-1.0.3.dist-info/METADATA
pieperkine-1.0.3.dist-info/WHEEL
pieperkine-1.0.3.dist-info/top_level.txt
pieperkine-1.0.3.dist-info/RECORD
