Metadata-Version: 2.4
Name: PieperKine
Version: 1.0.3
Summary: Inverse Kinematics Based on the Pieper Method
Home-page: https://github.com/Frank/PieperKine
Author: Frank
Classifier: Programming Language :: Python :: 3
Classifier: Operating System :: OS Independent
Requires-Python: >=3.10,<3.11
Requires-Dist: numpy
Requires-Dist: scipy
Dynamic: author
Dynamic: classifier
Dynamic: description
Dynamic: description-content-type
Dynamic: home-page
Dynamic: requires-dist
Dynamic: requires-python
Dynamic: summary
